{
  "nodes": [
    {
      "id": "thirdparty_vcpkg_versions_e_enchantum_json",
      "label": "enchantum.json",
      "file_type": "code",
      "source_file": "ThirdParty/vcpkg/versions/e-/enchantum.json",
      "source_location": "L1"
    },
    {
      "id": "e_enchantum_versions",
      "label": "versions",
      "file_type": "code",
      "source_file": "ThirdParty/vcpkg/versions/e-/enchantum.json",
      "source_location": "L2"
    }
  ],
  "edges": [
    {
      "source": "thirdparty_vcpkg_versions_e_enchantum_json",
      "target": "e_enchantum_versions",
      "relation": "contains",
      "confidence": "EXTRACTED",
      "source_file": "ThirdParty/vcpkg/versions/e-/enchantum.json",
      "source_location": "L2",
      "weight": 1.0
    }
  ]
}
