{
  "nodes": [
    {
      "id": "thirdparty_vcpkg_versions_i_infoware_json",
      "label": "infoware.json",
      "file_type": "code",
      "source_file": "ThirdParty/vcpkg/versions/i-/infoware.json",
      "source_location": "L1"
    },
    {
      "id": "i_infoware_versions",
      "label": "versions",
      "file_type": "code",
      "source_file": "ThirdParty/vcpkg/versions/i-/infoware.json",
      "source_location": "L2"
    }
  ],
  "edges": [
    {
      "source": "thirdparty_vcpkg_versions_i_infoware_json",
      "target": "i_infoware_versions",
      "relation": "contains",
      "confidence": "EXTRACTED",
      "source_file": "ThirdParty/vcpkg/versions/i-/infoware.json",
      "source_location": "L2",
      "weight": 1.0
    }
  ]
}
