{
  "nodes": [
    {
      "id": "thirdparty_vcpkg_versions_s_spirv_reflect_json",
      "label": "spirv-reflect.json",
      "file_type": "code",
      "source_file": "ThirdParty/vcpkg/versions/s-/spirv-reflect.json",
      "source_location": "L1"
    },
    {
      "id": "s_spirv_reflect_versions",
      "label": "versions",
      "file_type": "code",
      "source_file": "ThirdParty/vcpkg/versions/s-/spirv-reflect.json",
      "source_location": "L2"
    }
  ],
  "edges": [
    {
      "source": "thirdparty_vcpkg_versions_s_spirv_reflect_json",
      "target": "s_spirv_reflect_versions",
      "relation": "contains",
      "confidence": "EXTRACTED",
      "source_file": "ThirdParty/vcpkg/versions/s-/spirv-reflect.json",
      "source_location": "L2",
      "weight": 1.0
    }
  ]
}
