{
  "nodes": [
    {
      "id": "thirdparty_vcpkg_ports_vxl_vcpkg_json",
      "label": "vcpkg.json",
      "file_type": "code",
      "source_file": "ThirdParty/vcpkg/ports/vxl/vcpkg.json",
      "source_location": "L1"
    },
    {
      "id": "vxl_vcpkg_name",
      "label": "name",
      "file_type": "code",
      "source_file": "ThirdParty/vcpkg/ports/vxl/vcpkg.json",
      "source_location": "L2"
    },
    {
      "id": "vxl_vcpkg_version",
      "label": "version",
      "file_type": "code",
      "source_file": "ThirdParty/vcpkg/ports/vxl/vcpkg.json",
      "source_location": "L3"
    },
    {
      "id": "vxl_vcpkg_description",
      "label": "description",
      "file_type": "code",
      "source_file": "ThirdParty/vcpkg/ports/vxl/vcpkg.json",
      "source_location": "L4"
    },
    {
      "id": "vxl_vcpkg_homepage",
      "label": "homepage",
      "file_type": "code",
      "source_file": "ThirdParty/vcpkg/ports/vxl/vcpkg.json",
      "source_location": "L5"
    },
    {
      "id": "vxl_vcpkg_license",
      "label": "license",
      "file_type": "code",
      "source_file": "ThirdParty/vcpkg/ports/vxl/vcpkg.json",
      "source_location": "L6"
    },
    {
      "id": "vxl_vcpkg_supports",
      "label": "supports",
      "file_type": "code",
      "source_file": "ThirdParty/vcpkg/ports/vxl/vcpkg.json",
      "source_location": "L7"
    },
    {
      "id": "vxl_vcpkg_dependencies",
      "label": "dependencies",
      "file_type": "code",
      "source_file": "ThirdParty/vcpkg/ports/vxl/vcpkg.json",
      "source_location": "L8"
    },
    {
      "id": "vxl_vcpkg_features",
      "label": "features",
      "file_type": "code",
      "source_file": "ThirdParty/vcpkg/ports/vxl/vcpkg.json",
      "source_location": "L26"
    },
    {
      "id": "vxl_vcpkg_features_core_imaging",
      "label": "core-imaging",
      "file_type": "code",
      "source_file": "ThirdParty/vcpkg/ports/vxl/vcpkg.json",
      "source_location": "L27"
    },
    {
      "id": "vxl_vcpkg_core_imaging_description",
      "label": "description",
      "file_type": "code",
      "source_file": "ThirdParty/vcpkg/ports/vxl/vcpkg.json",
      "source_location": "L28"
    },
    {
      "id": "vxl_vcpkg_features_openjpeg",
      "label": "openjpeg",
      "file_type": "code",
      "source_file": "ThirdParty/vcpkg/ports/vxl/vcpkg.json",
      "source_location": "L30"
    },
    {
      "id": "vxl_vcpkg_openjpeg_description",
      "label": "description",
      "file_type": "code",
      "source_file": "ThirdParty/vcpkg/ports/vxl/vcpkg.json",
      "source_location": "L31"
    },
    {
      "id": "vxl_vcpkg_openjpeg_license",
      "label": "license",
      "file_type": "code",
      "source_file": "ThirdParty/vcpkg/ports/vxl/vcpkg.json",
      "source_location": "L35"
    },
    {
      "id": "vxl_vcpkg_openjpeg_dependencies",
      "label": "dependencies",
      "file_type": "code",
      "source_file": "ThirdParty/vcpkg/ports/vxl/vcpkg.json",
      "source_location": "L36"
    }
  ],
  "edges": [
    {
      "source": "thirdparty_vcpkg_ports_vxl_vcpkg_json",
      "target": "vxl_vcpkg_name",
      "relation": "contains",
      "confidence": "EXTRACTED",
      "source_file": "ThirdParty/vcpkg/ports/vxl/vcpkg.json",
      "source_location": "L2",
      "weight": 1.0
    },
    {
      "source": "thirdparty_vcpkg_ports_vxl_vcpkg_json",
      "target": "vxl_vcpkg_version",
      "relation": "contains",
      "confidence": "EXTRACTED",
      "source_file": "ThirdParty/vcpkg/ports/vxl/vcpkg.json",
      "source_location": "L3",
      "weight": 1.0
    },
    {
      "source": "thirdparty_vcpkg_ports_vxl_vcpkg_json",
      "target": "vxl_vcpkg_description",
      "relation": "contains",
      "confidence": "EXTRACTED",
      "source_file": "ThirdParty/vcpkg/ports/vxl/vcpkg.json",
      "source_location": "L4",
      "weight": 1.0
    },
    {
      "source": "thirdparty_vcpkg_ports_vxl_vcpkg_json",
      "target": "vxl_vcpkg_homepage",
      "relation": "contains",
      "confidence": "EXTRACTED",
      "source_file": "ThirdParty/vcpkg/ports/vxl/vcpkg.json",
      "source_location": "L5",
      "weight": 1.0
    },
    {
      "source": "thirdparty_vcpkg_ports_vxl_vcpkg_json",
      "target": "vxl_vcpkg_license",
      "relation": "contains",
      "confidence": "EXTRACTED",
      "source_file": "ThirdParty/vcpkg/ports/vxl/vcpkg.json",
      "source_location": "L6",
      "weight": 1.0
    },
    {
      "source": "thirdparty_vcpkg_ports_vxl_vcpkg_json",
      "target": "vxl_vcpkg_supports",
      "relation": "contains",
      "confidence": "EXTRACTED",
      "source_file": "ThirdParty/vcpkg/ports/vxl/vcpkg.json",
      "source_location": "L7",
      "weight": 1.0
    },
    {
      "source": "thirdparty_vcpkg_ports_vxl_vcpkg_json",
      "target": "vxl_vcpkg_dependencies",
      "relation": "contains",
      "confidence": "EXTRACTED",
      "source_file": "ThirdParty/vcpkg/ports/vxl/vcpkg.json",
      "source_location": "L8",
      "weight": 1.0
    },
    {
      "source": "vxl_vcpkg_dependencies",
      "target": "ref_libgeotiff",
      "relation": "extends",
      "confidence": "EXTRACTED",
      "source_file": "ThirdParty/vcpkg/ports/vxl/vcpkg.json",
      "source_location": "L8",
      "weight": 1.0,
      "context": "import"
    },
    {
      "source": "vxl_vcpkg_dependencies",
      "target": "ref_libjpeg_turbo",
      "relation": "extends",
      "confidence": "EXTRACTED",
      "source_file": "ThirdParty/vcpkg/ports/vxl/vcpkg.json",
      "source_location": "L8",
      "weight": 1.0,
      "context": "import"
    },
    {
      "source": "vxl_vcpkg_dependencies",
      "target": "ref_libpng",
      "relation": "extends",
      "confidence": "EXTRACTED",
      "source_file": "ThirdParty/vcpkg/ports/vxl/vcpkg.json",
      "source_location": "L8",
      "weight": 1.0,
      "context": "import"
    },
    {
      "source": "vxl_vcpkg_dependencies",
      "target": "ref_polyclipping",
      "relation": "extends",
      "confidence": "EXTRACTED",
      "source_file": "ThirdParty/vcpkg/ports/vxl/vcpkg.json",
      "source_location": "L8",
      "weight": 1.0,
      "context": "import"
    },
    {
      "source": "thirdparty_vcpkg_ports_vxl_vcpkg_json",
      "target": "vxl_vcpkg_features",
      "relation": "contains",
      "confidence": "EXTRACTED",
      "source_file": "ThirdParty/vcpkg/ports/vxl/vcpkg.json",
      "source_location": "L26",
      "weight": 1.0
    },
    {
      "source": "vxl_vcpkg_features",
      "target": "vxl_vcpkg_features_core_imaging",
      "relation": "contains",
      "confidence": "EXTRACTED",
      "source_file": "ThirdParty/vcpkg/ports/vxl/vcpkg.json",
      "source_location": "L27",
      "weight": 1.0
    },
    {
      "source": "vxl_vcpkg_features_core_imaging",
      "target": "vxl_vcpkg_core_imaging_description",
      "relation": "contains",
      "confidence": "EXTRACTED",
      "source_file": "ThirdParty/vcpkg/ports/vxl/vcpkg.json",
      "source_location": "L28",
      "weight": 1.0
    },
    {
      "source": "vxl_vcpkg_features",
      "target": "vxl_vcpkg_features_openjpeg",
      "relation": "contains",
      "confidence": "EXTRACTED",
      "source_file": "ThirdParty/vcpkg/ports/vxl/vcpkg.json",
      "source_location": "L30",
      "weight": 1.0
    },
    {
      "source": "vxl_vcpkg_features_openjpeg",
      "target": "vxl_vcpkg_openjpeg_description",
      "relation": "contains",
      "confidence": "EXTRACTED",
      "source_file": "ThirdParty/vcpkg/ports/vxl/vcpkg.json",
      "source_location": "L31",
      "weight": 1.0
    },
    {
      "source": "vxl_vcpkg_openjpeg_description",
      "target": "ref_openjpeg_support",
      "relation": "extends",
      "confidence": "EXTRACTED",
      "source_file": "ThirdParty/vcpkg/ports/vxl/vcpkg.json",
      "source_location": "L31",
      "weight": 1.0,
      "context": "import"
    },
    {
      "source": "vxl_vcpkg_openjpeg_description",
      "target": "ref_this_feature_uses_vendored_copy_of_openjpeg_1_2_0_and_cannot_be_used_together_with_port_openjpeg",
      "relation": "extends",
      "confidence": "EXTRACTED",
      "source_file": "ThirdParty/vcpkg/ports/vxl/vcpkg.json",
      "source_location": "L31",
      "weight": 1.0,
      "context": "import"
    },
    {
      "source": "vxl_vcpkg_features_openjpeg",
      "target": "vxl_vcpkg_openjpeg_license",
      "relation": "contains",
      "confidence": "EXTRACTED",
      "source_file": "ThirdParty/vcpkg/ports/vxl/vcpkg.json",
      "source_location": "L35",
      "weight": 1.0
    },
    {
      "source": "vxl_vcpkg_features_openjpeg",
      "target": "vxl_vcpkg_openjpeg_dependencies",
      "relation": "contains",
      "confidence": "EXTRACTED",
      "source_file": "ThirdParty/vcpkg/ports/vxl/vcpkg.json",
      "source_location": "L36",
      "weight": 1.0
    }
  ]
}
