{
  "nodes": [
    {
      "id": "thirdparty_vcpkg_versions_c_cartographer_json",
      "label": "cartographer.json",
      "file_type": "code",
      "source_file": "ThirdParty/vcpkg/versions/c-/cartographer.json",
      "source_location": "L1"
    },
    {
      "id": "c_cartographer_versions",
      "label": "versions",
      "file_type": "code",
      "source_file": "ThirdParty/vcpkg/versions/c-/cartographer.json",
      "source_location": "L2"
    }
  ],
  "edges": [
    {
      "source": "thirdparty_vcpkg_versions_c_cartographer_json",
      "target": "c_cartographer_versions",
      "relation": "contains",
      "confidence": "EXTRACTED",
      "source_file": "ThirdParty/vcpkg/versions/c-/cartographer.json",
      "source_location": "L2",
      "weight": 1.0
    }
  ]
}
