{
  "nodes": [
    {
      "id": "thirdparty_vcpkg_versions_c_cpptoml_json",
      "label": "cpptoml.json",
      "file_type": "code",
      "source_file": "ThirdParty/vcpkg/versions/c-/cpptoml.json",
      "source_location": "L1"
    },
    {
      "id": "c_cpptoml_versions",
      "label": "versions",
      "file_type": "code",
      "source_file": "ThirdParty/vcpkg/versions/c-/cpptoml.json",
      "source_location": "L2"
    }
  ],
  "edges": [
    {
      "source": "thirdparty_vcpkg_versions_c_cpptoml_json",
      "target": "c_cpptoml_versions",
      "relation": "contains",
      "confidence": "EXTRACTED",
      "source_file": "ThirdParty/vcpkg/versions/c-/cpptoml.json",
      "source_location": "L2",
      "weight": 1.0
    }
  ]
}
