{
  "nodes": [
    {
      "id": "thirdparty_vcpkg_versions_l_libpq_json",
      "label": "libpq.json",
      "file_type": "code",
      "source_file": "ThirdParty/vcpkg/versions/l-/libpq.json",
      "source_location": "L1"
    },
    {
      "id": "l_libpq_versions",
      "label": "versions",
      "file_type": "code",
      "source_file": "ThirdParty/vcpkg/versions/l-/libpq.json",
      "source_location": "L2"
    }
  ],
  "edges": [
    {
      "source": "thirdparty_vcpkg_versions_l_libpq_json",
      "target": "l_libpq_versions",
      "relation": "contains",
      "confidence": "EXTRACTED",
      "source_file": "ThirdParty/vcpkg/versions/l-/libpq.json",
      "source_location": "L2",
      "weight": 1.0
    }
  ]
}
