{
  "nodes": [
    {
      "id": "thirdparty_vcpkg_versions_n_nmslib_json",
      "label": "nmslib.json",
      "file_type": "code",
      "source_file": "ThirdParty/vcpkg/versions/n-/nmslib.json",
      "source_location": "L1"
    },
    {
      "id": "n_nmslib_versions",
      "label": "versions",
      "file_type": "code",
      "source_file": "ThirdParty/vcpkg/versions/n-/nmslib.json",
      "source_location": "L2"
    }
  ],
  "edges": [
    {
      "source": "thirdparty_vcpkg_versions_n_nmslib_json",
      "target": "n_nmslib_versions",
      "relation": "contains",
      "confidence": "EXTRACTED",
      "source_file": "ThirdParty/vcpkg/versions/n-/nmslib.json",
      "source_location": "L2",
      "weight": 1.0
    }
  ]
}
